setup.py
snailwebs/__init__.py
snailwebs.egg-info/PKG-INFO
snailwebs.egg-info/SOURCES.txt
snailwebs.egg-info/dependency_links.txt
snailwebs.egg-info/top_level.txt