Metadata-Version: 1.0
Name: snailwebs
Version: 0.0.1
Summary: Python工具
Home-page: UNKNOWN
Author: snail
Author-email: snail_email@163.com
License: UNKNOWN
Platform: UNKNOWN
